[{"Project Name": "29 BLVD T1", "Unit Number": "3004", "ROOMS DESCRIPTION": "1 B/R", "Size": "800 Sq.Ft", "Type ": "Apartments", "Location": "Downtown Dubai"}, {"Project Name": "29 BLVD T1", "Unit Number": "3005", "ROOMS DESCRIPTION": "1 B/R", "Size": "837 Sq.Ft", "Type ": "Apartments", "Location": "Downtown Dubai"}, {"Project Name": "29 BLVD T1", "Unit Number": "3007", "ROOMS DESCRIPTION": "1 B/R", "Size": "877 Sq.Ft", "Type ": "Apartments", "Location": "Downtown Dubai"}, {"Project Name": "29 BLVD T1", "Unit Number": "3008", "ROOMS DESCRIPTION": "1 B/R", "Size": "860 Sq.Ft", "Type ": "Apartments", "Location": "Downtown Dubai"}, {"Project Name": "29 BLVD T1", "Unit Number": "3101", "ROOMS DESCRIPTION": "1 B/R", "Size": "835 Sq.Ft", "Type ": "Apartments", "Location": "Downtown Dubai"}, {"Project Name": "29 BLVD T1", "Unit Number": "3102", "ROOMS DESCRIPTION": "1 B/R", "Size": "793 Sq.Ft", "Type ": "Apartments", "Location": "Downtown Dubai"}, {"Project Name": "29 BLVD T1", "Unit Number": "3104", "ROOMS DESCRIPTION": "1 B/R", "Size": "800 Sq.Ft", "Type ": "Apartments", "Location": "Downtown Dubai"}, {"Project Name": "29 BLVD T1", "Unit Number": "3105", "ROOMS DESCRIPTION": "1 B/R", "Size": "837 Sq.Ft", "Type ": "Apartments", "Location": "Downtown Dubai"}, {"Project Name": "29 BLVD T1", "Unit Number": "3107", "ROOMS DESCRIPTION": "1 B/R", "Size": "877 Sq.Ft", "Type ": "Apartments", "Location": "Downtown Dubai"}, {"Project Name": "29 BLVD T1", "Unit Number": "3108", "ROOMS DESCRIPTION": "1 B/R", "Size": "860 Sq.Ft", "Type ": "Apartments", "Location": "Downtown Dubai"}, {"Project Name": "29 BLVD T1", "Unit Number": "3201", "ROOMS DESCRIPTION": "1 B/R", "Size": "836 Sq.Ft", "Type ": "Apartments", "Location": "Downtown Dubai"}, {"Project Name": "29 BLVD T1", "Unit Number": "3202", "ROOMS DESCRIPTION": "1 B/R", "Size": "793 Sq.Ft", "Type ": "Apartments", "Location": "Downtown Dubai"}, {"Project Name": "29 BLVD T1", "Unit Number": "3204", "ROOMS DESCRIPTION": "1 B/R", "Size": "798 Sq.Ft", "Type ": "Apartments", "Location": "Downtown Dubai"}, {"Project Name": "29 BLVD T1", "Unit Number": "3205", "ROOMS DESCRIPTION": "1 B/R", "Size": "837 Sq.Ft", "Type ": "Apartments", "Location": "Downtown Dubai"}, {"Project Name": "29 BLVD T1", "Unit Number": "3208", "ROOMS DESCRIPTION": "1 B/R", "Size": "860 Sq.Ft", "Type ": "Apartments", "Location": "Downtown Dubai"}, {"Project Name": "29 BLVD T1", "Unit Number": "1901", "ROOMS DESCRIPTION": "1 B/R", "Size": "836 Sq.Ft", "Type ": "Apartments", "Location": "Downtown Dubai"}, {"Project Name": "29 BLVD T1", "Unit Number": "1902", "ROOMS DESCRIPTION": "1 B/R", "Size": "793 Sq.Ft", "Type ": "Apartments", "Location": "Downtown Dubai"}, {"Project Name": "29 BLVD T1", "Unit Number": "3706", "ROOMS DESCRIPTION": "1 B/R", "Size": "802 Sq.Ft", "Type ": "Apartments", "Location": "Downtown Dubai"}, {"Project Name": "29 BLVD T1", "Unit Number": "3801", "ROOMS DESCRIPTION": "1 B/R", "Size": "1056 Sq.Ft", "Type ": "Apartments", "Location": "Downtown Dubai"}, {"Project Name": "29 BLVD T1", "Unit Number": "3802", "ROOMS DESCRIPTION": "1 B/R", "Size": "1087 Sq.Ft", "Type ": "Apartments", "Location": "Downtown Dubai"}, {"Project Name": "29 BLVD T1", "Unit Number": "3803", "ROOMS DESCRIPTION": "1 B/R", "Size": "770 Sq.Ft", "Type ": "Apartments", "Location": "Downtown Dubai"}, {"Project Name": "29 BLVD T1", "Unit Number": "3806", "ROOMS DESCRIPTION": "1 B/R", "Size": "802 Sq.Ft", "Type ": "Apartments", "Location": "Downtown Dubai"}, {"Project Name": "29 BLVD T1", "Unit Number": "3901", "ROOMS DESCRIPTION": "1 B/R", "Size": "1056 Sq.Ft", "Type ": "Apartments", "Location": "Downtown Dubai"}, {"Project Name": "29 BLVD T1", "Unit Number": "3902", "ROOMS DESCRIPTION": "1 B/R", "Size": "1087 Sq.Ft", "Type ": "Apartments", "Location": "Downtown Dubai"}, {"Project Name": "29 BLVD T1", "Unit Number": "3903", "ROOMS DESCRIPTION": "1 B/R", "Size": "770 Sq.Ft", "Type ": "Apartments", "Location": "Downtown Dubai"}, {"Project Name": "29 BLVD T1", "Unit Number": "3906", "ROOMS DESCRIPTION": "1 B/R", "Size": "802 Sq.Ft", "Type ": "Apartments", "Location": "Downtown Dubai"}, {"Project Name": "29 BLVD T1", "Unit Number": "604", "ROOMS DESCRIPTION": "1 B/R", "Size": "799 Sq.Ft", "Type ": "Apartments", "Location": "Downtown Dubai"}, {"Project Name": "29 BLVD T1", "Unit Number": "605", "ROOMS DESCRIPTION": "1 B/R", "Size": "838 Sq.Ft", "Type ": "Apartments", "Location": "Downtown Dubai"}, {"Project Name": "29 BLVD T1", "Unit Number": "504", "ROOMS DESCRIPTION": "1 B/R", "Size": "838 Sq.Ft", "Type ": "Apartments", "Location": "Downtown Dubai"}, {"Project Name": "29 BLVD T1", "Unit Number": "1102", "ROOMS DESCRIPTION": "1 B/R", "Size": "793 Sq.Ft", "Type ": "Apartments", "Location": "Downtown Dubai"}, {"Project Name": "29 BLVD T1", "Unit Number": "1104", "ROOMS DESCRIPTION": "1 B/R", "Size": "799 Sq.Ft", "Type ": "Apartments", "Location": "Downtown Dubai"}, {"Project Name": "29 BLVD T1", "Unit Number": "1105", "ROOMS DESCRIPTION": "1 B/R", "Size": "838 Sq.Ft", "Type ": "Apartments", "Location": "Downtown Dubai"}, {"Project Name": "29 BLVD T1", "Unit Number": "601", "ROOMS DESCRIPTION": "1 B/R", "Size": "836 Sq.Ft", "Type ": "Apartments", "Location": "Downtown Dubai"}, {"Project Name": "29 BLVD T1", "Unit Number": "602", "ROOMS DESCRIPTION": "1 B/R", "Size": "793 Sq.Ft", "Type ": "Apartments", "Location": "Downtown Dubai"}, {"Project Name": "29 BLVD T1", "Unit Number": "3301", "ROOMS DESCRIPTION": "1 B/R", "Size": "1668 Sq.Ft", "Type ": "Apartments", "Location": "Downtown Dubai"}, {"Project Name": "29 BLVD T1", "Unit Number": "3302", "ROOMS DESCRIPTION": "1 B/R", "Size": "1699 Sq.Ft", "Type ": "Apartments", "Location": "Downtown Dubai"}, {"Project Name": "29 BLVD T1", "Unit Number": "3303", "ROOMS DESCRIPTION": "1 B/R", "Size": "874 Sq.Ft", "Type ": "Apartments", "Location": "Downtown Dubai"}, {"Project Name": "29 BLVD T1", "Unit Number": "3306", "ROOMS DESCRIPTION": "1 B/R", "Size": "905 Sq.Ft", "Type ": "Apartments", "Location": "Downtown Dubai"}, {"Project Name": "29 BLVD T1", "Unit Number": "3401", "ROOMS DESCRIPTION": "1 B/R", "Size": "1056 Sq.Ft", "Type ": "Apartments", "Location": "Downtown Dubai"}, {"Project Name": "29 BLVD T1", "Unit Number": "3402", "ROOMS DESCRIPTION": "1 B/R", "Size": "1087 Sq.Ft", "Type ": "Apartments", "Location": "Downtown Dubai"}, {"Project Name": "29 BLVD T1", "Unit Number": "3403", "ROOMS DESCRIPTION": "1 B/R", "Size": "770 Sq.Ft", "Type ": "Apartments", "Location": "Downtown Dubai"}, {"Project Name": "29 BLVD T1", "Unit Number": "3406", "ROOMS DESCRIPTION": "1 B/R", "Size": "802 Sq.Ft", "Type ": "Apartments", "Location": "Downtown Dubai"}, {"Project Name": "29 BLVD T1", "Unit Number": "3501", "ROOMS DESCRIPTION": "1 B/R", "Size": "1056 Sq.Ft", "Type ": "Apartments", "Location": "Downtown Dubai"}, {"Project Name": "29 BLVD T1", "Unit Number": "3502", "ROOMS DESCRIPTION": "1 B/R", "Size": "1087 Sq.Ft", "Type ": "Apartments", "Location": "Downtown Dubai"}, {"Project Name": "29 BLVD T1", "Unit Number": "3503", "ROOMS DESCRIPTION": "1 B/R", "Size": "770 Sq.Ft", "Type ": "Apartments", "Location": "Downtown Dubai"}, {"Project Name": "29 BLVD T1", "Unit Number": "701", "ROOMS DESCRIPTION": "1 B/R", "Size": "836 Sq.Ft", "Type ": "Apartments", "Location": "Downtown Dubai"}, {"Project Name": "29 BLVD T1", "Unit Number": "702", "ROOMS DESCRIPTION": "1 B/R", "Size": "793 Sq.Ft", "Type ": "Apartments", "Location": "Downtown Dubai"}, {"Project Name": "29 BLVD T1", "Unit Number": "704", "ROOMS DESCRIPTION": "1 B/R", "Size": "799 Sq.Ft", "Type ": "Apartments", "Location": "Downtown Dubai"}, {"Project Name": "29 BLVD T1", "Unit Number": "705", "ROOMS DESCRIPTION": "1 B/R", "Size": "838 Sq.Ft", "Type ": "Apartments", "Location": "Downtown Dubai"}, {"Project Name": "29 BLVD T1", "Unit Number": "801", "ROOMS DESCRIPTION": "1 B/R", "Size": "836 Sq.Ft", "Type ": "Apartments", "Location": "Downtown Dubai"}, {"Project Name": "29 BLVD T1", "Unit Number": "802", "ROOMS DESCRIPTION": "1 B/R", "Size": "793 Sq.Ft", "Type ": "Apartments", "Location": "Downtown Dubai"}, {"Project Name": "29 BLVD T1", "Unit Number": "804", "ROOMS DESCRIPTION": "1 B/R", "Size": "799 Sq.Ft", "Type ": "Apartments", "Location": "Downtown Dubai"}, {"Project Name": "29 BLVD T1", "Unit Number": "805", "ROOMS DESCRIPTION": "1 B/R", "Size": "838 Sq.Ft", "Type ": "Apartments", "Location": "Downtown Dubai"}, {"Project Name": "29 BLVD T1", "Unit Number": "1301", "ROOMS DESCRIPTION": "1 B/R", "Size": "836 Sq.Ft", "Type ": "Apartments", "Location": "Downtown Dubai"}, {"Project Name": "29 BLVD T1", "Unit Number": "1302", "ROOMS DESCRIPTION": "1 B/R", "Size": "793 Sq.Ft", "Type ": "Apartments", "Location": "Downtown Dubai"}, {"Project Name": "29 BLVD T1", "Unit Number": "1304", "ROOMS DESCRIPTION": "1 B/R", "Size": "799 Sq.Ft", "Type ": "Apartments", "Location": "Downtown Dubai"}, {"Project Name": "29 BLVD T1", "Unit Number": "1305", "ROOMS DESCRIPTION": "1 B/R", "Size": "838 Sq.Ft", "Type ": "Apartments", "Location": "Downtown Dubai"}, {"Project Name": "29 BLVD T1", "Unit Number": "1401", "ROOMS DESCRIPTION": "1 B/R", "Size": "836 Sq.Ft", "Type ": "Apartments", "Location": "Downtown Dubai"}, {"Project Name": "29 BLVD T1", "Unit Number": "2705", "ROOMS DESCRIPTION": "1 B/R", "Size": "838 Sq.Ft", "Type ": "Apartments", "Location": "Downtown Dubai"}, {"Project Name": "29 BLVD T1", "Unit Number": "2801", "ROOMS DESCRIPTION": "1 B/R", "Size": "836 Sq.Ft", "Type ": "Apartments", "Location": "Downtown Dubai"}, {"Project Name": "29 BLVD T1", "Unit Number": "2802", "ROOMS DESCRIPTION": "1 B/R", "Size": "793 Sq.Ft", "Type ": "Apartments", "Location": "Downtown Dubai"}, {"Project Name": "29 BLVD T1", "Unit Number": "2804", "ROOMS DESCRIPTION": "1 B/R", "Size": "800 Sq.Ft", "Type ": "Apartments", "Location": "Downtown Dubai"}, {"Project Name": "29 BLVD T1", "Unit Number": "2805", "ROOMS DESCRIPTION": "1 B/R", "Size": "838 Sq.Ft", "Type ": "Apartments", "Location": "Downtown Dubai"}, {"Project Name": "29 BLVD T1", "Unit Number": "2901", "ROOMS DESCRIPTION": "1 B/R", "Size": "836 Sq.Ft", "Type ": "Apartments", "Location": "Downtown Dubai"}, {"Project Name": "29 BLVD T1", "Unit Number": "2902", "ROOMS DESCRIPTION": "1 B/R", "Size": "793 Sq.Ft", "Type ": "Apartments", "Location": "Downtown Dubai"}, {"Project Name": "29 BLVD T1", "Unit Number": "2904", "ROOMS DESCRIPTION": "1 B/R", "Size": "800 Sq.Ft", "Type ": "Apartments", "Location": "Downtown Dubai"}, {"Project Name": "29 BLVD T1", "Unit Number": "2905", "ROOMS DESCRIPTION": "1 B/R", "Size": "837 Sq.Ft", "Type ": "Apartments", "Location": "Downtown Dubai"}, {"Project Name": "29 BLVD T1", "Unit Number": "2907", "ROOMS DESCRIPTION": "1 B/R", "Size": "1023 Sq.Ft", "Type ": "Apartments", "Location": "Downtown Dubai"}, {"Project Name": "29 BLVD T1", "Unit Number": "2908", "ROOMS DESCRIPTION": "1 B/R", "Size": "1006 Sq.Ft", "Type ": "Apartments", "Location": "Downtown Dubai"}, {"Project Name": "29 BLVD T1", "Unit Number": "3001", "ROOMS DESCRIPTION": "1 B/R", "Size": "835 Sq.Ft", "Type ": "Apartments", "Location": "Downtown Dubai"}, {"Project Name": "29 BLVD T1", "Unit Number": "3002", "ROOMS DESCRIPTION": "1 B/R", "Size": "793 Sq.Ft", "Type ": "Apartments", "Location": "Downtown Dubai"}, {"Project Name": "29 BLVD T1", "Unit Number": "1201", "ROOMS DESCRIPTION": "1 B/R", "Size": "836 Sq.Ft", "Type ": "Apartments", "Location": "Downtown Dubai"}, {"Project Name": "29 BLVD T1", "Unit Number": "1202", "ROOMS DESCRIPTION": "1 B/R", "Size": "793 Sq.Ft", "Type ": "Apartments", "Location": "Downtown Dubai"}, {"Project Name": "29 BLVD T1", "Unit Number": "1204", "ROOMS DESCRIPTION": "1 B/R", "Size": "799 Sq.Ft", "Type ": "Apartments", "Location": "Downtown Dubai"}, {"Project Name": "29 BLVD T1", "Unit Number": "1205", "ROOMS DESCRIPTION": "1 B/R", "Size": "838 Sq.Ft", "Type ": "Apartments", "Location": "Downtown Dubai"}, {"Project Name": "29 BLVD T1", "Unit Number": "1904", "ROOMS DESCRIPTION": "1 B/R", "Size": "799 Sq.Ft", "Type ": "Apartments", "Location": "Downtown Dubai"}, {"Project Name": "29 BLVD T1", "Unit Number": "1905", "ROOMS DESCRIPTION": "1 B/R", "Size": "838 Sq.Ft", "Type ": "Apartments", "Location": "Downtown Dubai"}, {"Project Name": "29 BLVD T1", "Unit Number": "2004", "ROOMS DESCRIPTION": "1 B/R", "Size": "799 Sq.Ft", "Type ": "Apartments", "Location": "Downtown Dubai"}, {"Project Name": "29 BLVD T1", "Unit Number": "2005", "ROOMS DESCRIPTION": "1 B/R", "Size": "838 Sq.Ft", "Type ": "Apartments", "Location": "Downtown Dubai"}, {"Project Name": "29 BLVD T1", "Unit Number": "2101", "ROOMS DESCRIPTION": "1 B/R", "Size": "836 Sq.Ft", "Type ": "Apartments", "Location": "Downtown Dubai"}, {"Project Name": "29 BLVD T1", "Unit Number": "3506", "ROOMS DESCRIPTION": "1 B/R", "Size": "802 Sq.Ft", "Type ": "Apartments", "Location": "Downtown Dubai"}, {"Project Name": "29 BLVD T1", "Unit Number": "3601", "ROOMS DESCRIPTION": "1 B/R", "Size": "1056 Sq.Ft", "Type ": "Apartments", "Location": "Downtown Dubai"}, {"Project Name": "29 BLVD T1", "Unit Number": "3602", "ROOMS DESCRIPTION": "1 B/R", "Size": "1087 Sq.Ft", "Type ": "Apartments", "Location": "Downtown Dubai"}, {"Project Name": "29 BLVD T1", "Unit Number": "3603", "ROOMS DESCRIPTION": "1 B/R", "Size": "770 Sq.Ft", "Type ": "Apartments", "Location": "Downtown Dubai"}, {"Project Name": "29 BLVD T1", "Unit Number": "4001", "ROOMS DESCRIPTION": "1 B/R", "Size": "1056 Sq.Ft", "Type ": "Apartments", "Location": "Downtown Dubai"}, {"Project Name": "29 BLVD T1", "Unit Number": "4002", "ROOMS DESCRIPTION": "1 B/R", "Size": "1087 Sq.Ft", "Type ": "Apartments", "Location": "Downtown Dubai"}, {"Project Name": "29 BLVD T1", "Unit Number": "4003", "ROOMS DESCRIPTION": "1 B/R", "Size": "770 Sq.Ft", "Type ": "Apartments", "Location": "Downtown Dubai"}, {"Project Name": "29 BLVD T1", "Unit Number": "4006", "ROOMS DESCRIPTION": "1 B/R", "Size": "802 Sq.Ft", "Type ": "Apartments", "Location": "Downtown Dubai"}, {"Project Name": "29 BLVD T1", "Unit Number": "4101", "ROOMS DESCRIPTION": "1 B/R", "Size": "1056 Sq.Ft", "Type ": "Apartments", "Location": "Downtown Dubai"}, {"Project Name": "29 BLVD T1", "Unit Number": "4102", "ROOMS DESCRIPTION": "1 B/R", "Size": "1087 Sq.Ft", "Type ": "Apartments", "Location": "Downtown Dubai"}, {"Project Name": "29 BLVD T1", "Unit Number": "4103", "ROOMS DESCRIPTION": "1 B/R", "Size": "770 Sq.Ft", "Type ": "Apartments", "Location": "Downtown Dubai"}, {"Project Name": "29 BLVD T1", "Unit Number": "4106", "ROOMS DESCRIPTION": "1 B/R", "Size": "802 Sq.Ft", "Type ": "Apartments", "Location": "Downtown Dubai"}, {"Project Name": "29 BLVD T1", "Unit Number": "4201", "ROOMS DESCRIPTION": "1 B/R", "Size": "1056 Sq.Ft", "Type ": "Apartments", "Location": "Downtown Dubai"}, {"Project Name": "29 BLVD T1", "Unit Number": "4202", "ROOMS DESCRIPTION": "1 B/R", "Size": "1087 Sq.Ft", "Type ": "Apartments", "Location": "Downtown Dubai"}, {"Project Name": "29 BLVD T1", "Unit Number": "4203", "ROOMS DESCRIPTION": "1 B/R", "Size": "770 Sq.Ft", "Type ": "Apartments", "Location": "Downtown Dubai"}, {"Project Name": "29 BLVD T1", "Unit Number": "4206", "ROOMS DESCRIPTION": "1 B/R", "Size": "802 Sq.Ft", "Type ": "Apartments", "Location": "Downtown Dubai"}, {"Project Name": "29 BLVD T1", "Unit Number": "3606", "ROOMS DESCRIPTION": "1 B/R", "Size": "802 Sq.Ft", "Type ": "Apartments", "Location": "Downtown Dubai"}, {"Project Name": "29 BLVD T1", "Unit Number": "3701", "ROOMS DESCRIPTION": "1 B/R", "Size": "1056 Sq.Ft", "Type ": "Apartments", "Location": "Downtown Dubai"}, {"Project Name": "29 BLVD T1", "Unit Number": "3702", "ROOMS DESCRIPTION": "1 B/R", "Size": "1087 Sq.Ft", "Type ": "Apartments", "Location": "Downtown Dubai"}, {"Project Name": "29 BLVD T1", "Unit Number": "3703", "ROOMS DESCRIPTION": "1 B/R", "Size": "770 Sq.Ft", "Type ": "Apartments", "Location": "Downtown Dubai"}, {"Project Name": "29 BLVD T1", "Unit Number": "901", "ROOMS DESCRIPTION": "1 B/R", "Size": "836 Sq.Ft", "Type ": "Apartments", "Location": "Downtown Dubai"}, {"Project Name": "29 BLVD T1", "Unit Number": "902", "ROOMS DESCRIPTION": "1 B/R", "Size": "793 Sq.Ft", "Type ": "Apartments", "Location": "Downtown Dubai"}, {"Project Name": "29 BLVD T1", "Unit Number": "904", "ROOMS DESCRIPTION": "1 B/R", "Size": "799 Sq.Ft", "Type ": "Apartments", "Location": "Downtown Dubai"}, {"Project Name": "29 BLVD T1", "Unit Number": "905", "ROOMS DESCRIPTION": "1 B/R", "Size": "838 Sq.Ft", "Type ": "Apartments", "Location": "Downtown Dubai"}, {"Project Name": "29 BLVD T1", "Unit Number": "1001", "ROOMS DESCRIPTION": "1 B/R", "Size": "836 Sq.Ft", "Type ": "Apartments", "Location": "Downtown Dubai"}, {"Project Name": "29 BLVD T1", "Unit Number": "1002", "ROOMS DESCRIPTION": "1 B/R", "Size": "793 Sq.Ft", "Type ": "Apartments", "Location": "Downtown Dubai"}, {"Project Name": "29 BLVD T1", "Unit Number": "1004", "ROOMS DESCRIPTION": "1 B/R", "Size": "799 Sq.Ft", "Type ": "Apartments", "Location": "Downtown Dubai"}, {"Project Name": "29 BLVD T1", "Unit Number": "1005", "ROOMS DESCRIPTION": "1 B/R", "Size": "838 Sq.Ft", "Type ": "Apartments", "Location": "Downtown Dubai"}, {"Project Name": "29 BLVD T1", "Unit Number": "1101", "ROOMS DESCRIPTION": "1 B/R", "Size": "836 Sq.Ft", "Type ": "Apartments", "Location": "Downtown Dubai"}, {"Project Name": "29 BLVD T1", "Unit Number": "302", "ROOMS DESCRIPTION": "1 B/R", "Size": "1671 Sq.Ft", "Type ": "Apartments", "Location": "Downtown Dubai"}, {"Project Name": "29 BLVD T1", "Unit Number": "402", "ROOMS DESCRIPTION": "1 B/R", "Size": "848 Sq.Ft", "Type ": "Apartments", "Location": "Downtown Dubai"}, {"Project Name": "29 BLVD T1", "Unit Number": "404", "ROOMS DESCRIPTION": "1 B/R", "Size": "838 Sq.Ft", "Type ": "Apartments", "Location": "Downtown Dubai"}, {"Project Name": "29 BLVD T1", "Unit Number": "501", "ROOMS DESCRIPTION": "1 B/R", "Size": "781 Sq.Ft", "Type ": "Apartments", "Location": "Downtown Dubai"}, {"Project Name": "29 BLVD T1", "Unit Number": "502", "ROOMS DESCRIPTION": "1 B/R", "Size": "848 Sq.Ft", "Type ": "Apartments", "Location": "Downtown Dubai"}, {"Project Name": "29 BLVD T1", "Unit Number": "1402", "ROOMS DESCRIPTION": "1 B/R", "Size": "793 Sq.Ft", "Type ": "Apartments", "Location": "Downtown Dubai"}, {"Project Name": "29 BLVD T1", "Unit Number": "1404", "ROOMS DESCRIPTION": "1 B/R", "Size": "799 Sq.Ft", "Type ": "Apartments", "Location": "Downtown Dubai"}, {"Project Name": "29 BLVD T1", "Unit Number": "1405", "ROOMS DESCRIPTION": "1 B/R", "Size": "838 Sq.Ft", "Type ": "Apartments", "Location": "Downtown Dubai"}, {"Project Name": "29 BLVD T1", "Unit Number": "1501", "ROOMS DESCRIPTION": "1 B/R", "Size": "836 Sq.Ft", "Type ": "Apartments", "Location": "Downtown Dubai"}, {"Project Name": "29 BLVD T1", "Unit Number": "1502", "ROOMS DESCRIPTION": "1 B/R", "Size": "793 Sq.Ft", "Type ": "Apartments", "Location": "Downtown Dubai"}, {"Project Name": "29 BLVD T1", "Unit Number": "1504", "ROOMS DESCRIPTION": "1 B/R", "Size": "799 Sq.Ft", "Type ": "Apartments", "Location": "Downtown Dubai"}, {"Project Name": "29 BLVD T1", "Unit Number": "1505", "ROOMS DESCRIPTION": "1 B/R", "Size": "838 Sq.Ft", "Type ": "Apartments", "Location": "Downtown Dubai"}, {"Project Name": "29 BLVD T1", "Unit Number": "1601", "ROOMS DESCRIPTION": "1 B/R", "Size": "836 Sq.Ft", "Type ": "Apartments", "Location": "Downtown Dubai"}, {"Project Name": "29 BLVD T1", "Unit Number": "1602", "ROOMS DESCRIPTION": "1 B/R", "Size": "793 Sq.Ft", "Type ": "Apartments", "Location": "Downtown Dubai"}, {"Project Name": "29 BLVD T1", "Unit Number": "1604", "ROOMS DESCRIPTION": "1 B/R", "Size": "799 Sq.Ft", "Type ": "Apartments", "Location": "Downtown Dubai"}, {"Project Name": "29 BLVD T1", "Unit Number": "1605", "ROOMS DESCRIPTION": "1 B/R", "Size": "838 Sq.Ft", "Type ": "Apartments", "Location": "Downtown Dubai"}, {"Project Name": "29 BLVD T1", "Unit Number": "1701", "ROOMS DESCRIPTION": "1 B/R", "Size": "836 Sq.Ft", "Type ": "Apartments", "Location": "Downtown Dubai"}, {"Project Name": "29 BLVD T1", "Unit Number": "1702", "ROOMS DESCRIPTION": "1 B/R", "Size": "793 Sq.Ft", "Type ": "Apartments", "Location": "Downtown Dubai"}, {"Project Name": "29 BLVD T1", "Unit Number": "1704", "ROOMS DESCRIPTION": "1 B/R", "Size": "799 Sq.Ft", "Type ": "Apartments", "Location": "Downtown Dubai"}, {"Project Name": "29 BLVD T1", "Unit Number": "1705", "ROOMS DESCRIPTION": "1 B/R", "Size": "838 Sq.Ft", "Type ": "Apartments", "Location": "Downtown Dubai"}, {"Project Name": "29 BLVD T1", "Unit Number": "1801", "ROOMS DESCRIPTION": "1 B/R", "Size": "836 Sq.Ft", "Type ": "Apartments", "Location": "Downtown Dubai"}, {"Project Name": "29 BLVD T1", "Unit Number": "1802", "ROOMS DESCRIPTION": "1 B/R", "Size": "793 Sq.Ft", "Type ": "Apartments", "Location": "Downtown Dubai"}, {"Project Name": "29 BLVD T1", "Unit Number": "1804", "ROOMS DESCRIPTION": "1 B/R", "Size": "799 Sq.Ft", "Type ": "Apartments", "Location": "Downtown Dubai"}, {"Project Name": "29 BLVD T1", "Unit Number": "1805", "ROOMS DESCRIPTION": "1 B/R", "Size": "838 Sq.Ft", "Type ": "Apartments", "Location": "Downtown Dubai"}, {"Project Name": "29 BLVD T1", "Unit Number": "2102", "ROOMS DESCRIPTION": "1 B/R", "Size": "793 Sq.Ft", "Type ": "Apartments", "Location": "Downtown Dubai"}, {"Project Name": "29 BLVD T1", "Unit Number": "2104", "ROOMS DESCRIPTION": "1 B/R", "Size": "799 Sq.Ft", "Type ": "Apartments", "Location": "Downtown Dubai"}, {"Project Name": "29 BLVD T1", "Unit Number": "2105", "ROOMS DESCRIPTION": "1 B/R", "Size": "838 Sq.Ft", "Type ": "Apartments", "Location": "Downtown Dubai"}, {"Project Name": "29 BLVD T1", "Unit Number": "2201", "ROOMS DESCRIPTION": "1 B/R", "Size": "836 Sq.Ft", "Type ": "Apartments", "Location": "Downtown Dubai"}, {"Project Name": "29 BLVD T1", "Unit Number": "2202", "ROOMS DESCRIPTION": "1 B/R", "Size": "793 Sq.Ft", "Type ": "Apartments", "Location": "Downtown Dubai"}, {"Project Name": "29 BLVD T1", "Unit Number": "2204", "ROOMS DESCRIPTION": "1 B/R", "Size": "799 Sq.Ft", "Type ": "Apartments", "Location": "Downtown Dubai"}, {"Project Name": "29 BLVD T1", "Unit Number": "2205", "ROOMS DESCRIPTION": "1 B/R", "Size": "838 Sq.Ft", "Type ": "Apartments", "Location": "Downtown Dubai"}, {"Project Name": "29 BLVD T1", "Unit Number": "2301", "ROOMS DESCRIPTION": "1 B/R", "Size": "836 Sq.Ft", "Type ": "Apartments", "Location": "Downtown Dubai"}, {"Project Name": "29 BLVD T1", "Unit Number": "2302", "ROOMS DESCRIPTION": "1 B/R", "Size": "793 Sq.Ft", "Type ": "Apartments", "Location": "Downtown Dubai"}, {"Project Name": "29 BLVD T1", "Unit Number": "2304", "ROOMS DESCRIPTION": "1 B/R", "Size": "799 Sq.Ft", "Type ": "Apartments", "Location": "Downtown Dubai"}, {"Project Name": "29 BLVD T1", "Unit Number": "2305", "ROOMS DESCRIPTION": "1 B/R", "Size": "838 Sq.Ft", "Type ": "Apartments", "Location": "Downtown Dubai"}, {"Project Name": "29 BLVD T1", "Unit Number": "2401", "ROOMS DESCRIPTION": "1 B/R", "Size": "836 Sq.Ft", "Type ": "Apartments", "Location": "Downtown Dubai"}, {"Project Name": "29 BLVD T1", "Unit Number": "2402", "ROOMS DESCRIPTION": "1 B/R", "Size": "793 Sq.Ft", "Type ": "Apartments", "Location": "Downtown Dubai"}, {"Project Name": "29 BLVD T1", "Unit Number": "2404", "ROOMS DESCRIPTION": "1 B/R", "Size": "799 Sq.Ft", "Type ": "Apartments", "Location": "Downtown Dubai"}, {"Project Name": "29 BLVD T1", "Unit Number": "2405", "ROOMS DESCRIPTION": "1 B/R", "Size": "838 Sq.Ft", "Type ": "Apartments", "Location": "Downtown Dubai"}, {"Project Name": "29 BLVD T1", "Unit Number": "2501", "ROOMS DESCRIPTION": "1 B/R", "Size": "836 Sq.Ft", "Type ": "Apartments", "Location": "Downtown Dubai"}, {"Project Name": "29 BLVD T1", "Unit Number": "2502", "ROOMS DESCRIPTION": "1 B/R", "Size": "793 Sq.Ft", "Type ": "Apartments", "Location": "Downtown Dubai"}, {"Project Name": "29 BLVD T1", "Unit Number": "2504", "ROOMS DESCRIPTION": "1 B/R", "Size": "800 Sq.Ft", "Type ": "Apartments", "Location": "Downtown Dubai"}, {"Project Name": "29 BLVD T1", "Unit Number": "2505", "ROOMS DESCRIPTION": "1 B/R", "Size": "838 Sq.Ft", "Type ": "Apartments", "Location": "Downtown Dubai"}, {"Project Name": "29 BLVD T1", "Unit Number": "2601", "ROOMS DESCRIPTION": "1 B/R", "Size": "836 Sq.Ft", "Type ": "Apartments", "Location": "Downtown Dubai"}, {"Project Name": "29 BLVD T1", "Unit Number": "2602", "ROOMS DESCRIPTION": "1 B/R", "Size": "793 Sq.Ft", "Type ": "Apartments", "Location": "Downtown Dubai"}, {"Project Name": "29 BLVD T1", "Unit Number": "2604", "ROOMS DESCRIPTION": "1 B/R", "Size": "800 Sq.Ft", "Type ": "Apartments", "Location": "Downtown Dubai"}, {"Project Name": "29 BLVD T1", "Unit Number": "2605", "ROOMS DESCRIPTION": "1 B/R", "Size": "838 Sq.Ft", "Type ": "Apartments", "Location": "Downtown Dubai"}, {"Project Name": "29 BLVD T1", "Unit Number": "2701", "ROOMS DESCRIPTION": "1 B/R", "Size": "836 Sq.Ft", "Type ": "Apartments", "Location": "Downtown Dubai"}, {"Project Name": "29 BLVD T1", "Unit Number": "2702", "ROOMS DESCRIPTION": "1 B/R", "Size": "793 Sq.Ft", "Type ": "Apartments", "Location": "Downtown Dubai"}, {"Project Name": "29 BLVD T1", "Unit Number": "2704", "ROOMS DESCRIPTION": "1 B/R", "Size": "800 Sq.Ft", "Type ": "Apartments", "Location": "Downtown Dubai"}, {"Project Name": "29 BLVD T1", "Unit Number": "2001", "ROOMS DESCRIPTION": "1 B/R", "Size": "836 Sq.Ft", "Type ": "Apartments", "Location": "Downtown Dubai"}, {"Project Name": "29 BLVD T1", "Unit Number": "2002", "ROOMS DESCRIPTION": "1 B/R", "Size": "793 Sq.Ft", "Type ": "Apartments", "Location": "Downtown Dubai"}]